neqs/__init__.py
neqs/_damped_newton.py
neqs/_firefly.py
neqs/_levenberg.py
neqs/_searches.py
neqs/iter_printers.py
neqs/iterative.py
neqs-0.9.0.dist-info/METADATA
neqs-0.9.0.dist-info/WHEEL
neqs-0.9.0.dist-info/licenses/LICENCE
neqs-0.9.0.dist-info/RECORD
