Metadata-Version: 2.4
Name: neqs
Version: 0.9.0
Summary: Newton-based nonlinear equation solvers
Project-URL: Homepage, https://github.com/iris-solutions-team/neqs
Project-URL: Documentation, https://iris-solutions-team.github.io/neqs-pages
Project-URL: Bug Tracker, https://github.com/iris-solutions-team/neqs/issues
Author-email: Jaromir Benes <jaromir.benes@gmail.com>, Ngoc Nam Nguyen <ngocnam.nguyen@ogresearch.com>
License-File: LICENCE
Keywords: modeling,numerical,simulation
Classifier: License :: OSI Approved :: MIT License
Classifier: Operating System :: OS Independent
Classifier: Programming Language :: Python :: 3
Requires-Python: >=3.12
Requires-Dist: numpy>=2.1
Requires-Dist: scipy>=1.14
